Compiled from "RunAnywhere+ModelManagement.jvmAndroid.kt"
public final class com.runanywhere.sdk.public.extensions.RunAnywhere_ModelManagement_jvmAndroidKt {
  public static final void registerModelInternal(com.runanywhere.sdk.public.extensions.Models.ModelInfo);
    Code:
       0: nop
       1: new           #11                 // class com/runanywhere/sdk/foundation/bridge/extensions/CppBridgeModelRegistry$ModelInfo
       4: dup
       5: aload_0
       6: invokevirtual #17                 // Method com/runanywhere/sdk/public/extensions/Models/ModelInfo.getId:()Ljava/lang/String;
       9: aload_0
      10: invokevirtual #20                 // Method com/runanywhere/sdk/public/extensions/Models/ModelInfo.getName:()Ljava/lang/String;
      13: aload_0
      14: invokevirtual #24                 // Method com/runanywhere/sdk/public/extensions/Models/ModelInfo.getCategory:()Lcom/runanywhere/sdk/public/extensions/Models/ModelCategory;
      17: getstatic     #30                 // Field com/runanywhere/sdk/public/extensions/RunAnywhere_ModelManagement_jvmAndroidKt$WhenMappings.$EnumSwitchMapping$0:[I
      20: swap
      21: invokevirtual #36                 // Method com/runanywhere/sdk/public/extensions/Models/ModelCategory.ordinal:()I
      24: iaload
      25: tableswitch   { // 1 to 4

                     1: 56

                     2: 60

                     3: 64

                     4: 68
               default: 72
          }
      56: iconst_0
      57: goto          73
      60: iconst_1
      61: goto          73
      64: iconst_2
      65: goto          73
      68: iconst_3
      69: goto          73
      72: iconst_0
      73: aload_0
      74: invokevirtual #40                 // Method com/runanywhere/sdk/public/extensions/Models/ModelInfo.getFormat:()Lcom/runanywhere/sdk/public/extensions/Models/ModelFormat;
      77: getstatic     #43                 // Field com/runanywhere/sdk/public/extensions/RunAnywhere_ModelManagement_jvmAndroidKt$WhenMappings.$EnumSwitchMapping$1:[I
      80: swap
      81: invokevirtual #46                 // Method com/runanywhere/sdk/public/extensions/Models/ModelFormat.ordinal:()I
      84: iaload
      85: tableswitch   { // 1 to 3

                     1: 112

                     2: 116

                     3: 120
               default: 124
          }
     112: iconst_1
     113: goto          125
     116: iconst_2
     117: goto          125
     120: iconst_3
     121: goto          125
     124: iconst_0
     125: aload_0
     126: invokevirtual #50                 // Method com/runanywhere/sdk/public/extensions/Models/ModelInfo.getFramework:()Lcom/runanywhere/sdk/core/types/InferenceFramework;
     129: getstatic     #53                 // Field com/runanywhere/sdk/public/extensions/RunAnywhere_ModelManagement_jvmAndroidKt$WhenMappings.$EnumSwitchMapping$2:[I
     132: swap
     133: invokevirtual #56                 // Method com/runanywhere/sdk/core/types/InferenceFramework.ordinal:()I
     136: iaload
     137: tableswitch   { // 1 to 8

                     1: 184

                     2: 188

                     3: 192

                     4: 196

                     5: 200

                     6: 204

                     7: 208

                     8: 213
               default: 218
          }
     184: iconst_1
     185: goto          226
     188: iconst_0
     189: goto          226
     192: iconst_2
     193: goto          226
     196: iconst_3
     197: goto          226
     200: iconst_4
     201: goto          226
     204: iconst_5
     205: goto          226
     208: bipush        6
     210: goto          226
     213: bipush        99
     215: goto          226
     218: new           #58                 // class kotlin/NoWhenBranchMatchedException
     221: dup
     222: invokespecial #62                 // Method kotlin/NoWhenBranchMatchedException."<init>":()V
     225: athrow
     226: aload_0
     227: invokevirtual #65                 // Method com/runanywhere/sdk/public/extensions/Models/ModelInfo.getDownloadURL:()Ljava/lang/String;
     230: aload_0
     231: invokevirtual #68                 // Method com/runanywhere/sdk/public/extensions/Models/ModelInfo.getLocalPath:()Ljava/lang/String;
     234: aload_0
     235: invokevirtual #72                 // Method com/runanywhere/sdk/public/extensions/Models/ModelInfo.getDownloadSize:()Ljava/lang/Long;
     238: dup
     239: ifnull        248
     242: invokevirtual #78                 // Method java/lang/Long.longValue:()J
     245: goto          250
     248: pop
     249: lconst_0
     250: aload_0
     251: invokevirtual #82                 // Method com/runanywhere/sdk/public/extensions/Models/ModelInfo.getContextLength:()Ljava/lang/Integer;
     254: dup
     255: ifnull        264
     258: invokevirtual #87                 // Method java/lang/Integer.intValue:()I
     261: goto          266
     264: pop
     265: iconst_0
     266: aload_0
     267: invokevirtual #91                 // Method com/runanywhere/sdk/public/extensions/Models/ModelInfo.getSupportsThinking:()Z
     270: aload_0
     271: invokevirtual #94                 // Method com/runanywhere/sdk/public/extensions/Models/ModelInfo.getDescription:()Ljava/lang/String;
     274: iconst_1
     275: invokespecial #97                 // Method com/runanywhere/sdk/foundation/bridge/extensions/CppBridgeModelRegistry$ModelInfo."<init>":(Ljava/lang/String;Ljava/lang/String;IIILjava/lang/String;Ljava/lang/String;JIZLjava/lang/String;I)V
     278: astore_1
     279: getstatic     #103                // Field com/runanywhere/sdk/foundation/bridge/extensions/CppBridgeModelRegistry.INSTANCE:Lcom/runanywhere/sdk/foundation/bridge/extensions/CppBridgeModelRegistry;
     282: aload_1
     283: invokevirtual #107                // Method com/runanywhere/sdk/foundation/bridge/extensions/CppBridgeModelRegistry.save:(Lcom/runanywhere/sdk/foundation/bridge/extensions/CppBridgeModelRegistry$ModelInfo;)V
     286: aload_0
     287: invokestatic  #110                // Method addToModelCache:(Lcom/runanywhere/sdk/public/extensions/Models/ModelInfo;)V
     290: getstatic     #114                // Field modelsLogger:Lcom/runanywhere/sdk/foundation/SDKLogger;
     293: aload_0
     294: invokevirtual #20                 // Method com/runanywhere/sdk/public/extensions/Models/ModelInfo.getName:()Ljava/lang/String;
     297: aload_0
     298: invokevirtual #17                 // Method com/runanywhere/sdk/public/extensions/Models/ModelInfo.getId:()Ljava/lang/String;
     301: invokedynamic #126,  0            // InvokeDynamic #0:makeConcatWithConstants:(Ljava/lang/String;Ljava/lang/String;)Ljava/lang/String;
     306: aconst_null
     307: iconst_2
     308: aconst_null
     309: invokestatic  #132                // Method com/runanywhere/sdk/foundation/SDKLogger.info$default:(Lcom/runanywhere/sdk/foundation/SDKLogger;Ljava/lang/String;Ljava/util/Map;ILjava/lang/Object;)V
     312: goto          336
     315: astore_1
     316: getstatic     #114                // Field modelsLogger:Lcom/runanywhere/sdk/foundation/SDKLogger;
     319: aload_1
     320: invokevirtual #135                // Method java/lang/Exception.getMessage:()Ljava/lang/String;
     323: invokedynamic #140,  0            // InvokeDynamic #1:makeConcatWithConstants:(Ljava/lang/String;)Ljava/lang/String;
     328: aconst_null
     329: aconst_null
     330: bipush        6
     332: aconst_null
     333: invokestatic  #144                // Method com/runanywhere/sdk/foundation/SDKLogger.error$default:(Lcom/runanywhere/sdk/foundation/SDKLogger;Ljava/lang/String;Ljava/util/Map;Ljava/lang/Throwable;ILjava/lang/Object;)V
     336: return
    Exception table:
       from    to  target type
           0   312   315   Class java/lang/Exception

  public static final java.lang.Object availableModels(com.runanywhere.sdk.public.RunAnywhere, kotlin.coroutines.Continuation<? super java.util.List<com.runanywhere.sdk.public.extensions.Models.ModelInfo>>);
    Code:
       0: aload_0
       1: invokevirtual #226                // Method com/runanywhere/sdk/public/RunAnywhere.isInitialized:()Z
       4: ifne          19
       7: getstatic     #232                // Field com/runanywhere/sdk/foundation/errors/SDKError.Companion:Lcom/runanywhere/sdk/foundation/errors/SDKError$Companion;
      10: ldc           #234                // String SDK not initialized
      12: aconst_null
      13: iconst_2
      14: aconst_null
      15: invokestatic  #240                // Method com/runanywhere/sdk/foundation/errors/SDKError$Companion.notInitialized$default:(Lcom/runanywhere/sdk/foundation/errors/SDKError$Companion;Ljava/lang/String;Ljava/lang/Throwable;ILjava/lang/Object;)Lcom/runanywhere/sdk/foundation/errors/SDKError;
      18: athrow
      19: getstatic     #243                // Field scanLock:Ljava/lang/Object;
      22: astore_3
      23: aload_3
      24: monitorenter
      25: nop
      26: iconst_0
      27: istore        4
      29: getstatic     #247                // Field hasScannedForDownloads:Z
      32: ifne          48
      35: getstatic     #103                // Field com/runanywhere/sdk/foundation/bridge/extensions/CppBridgeModelRegistry.INSTANCE:Lcom/runanywhere/sdk/foundation/bridge/extensions/CppBridgeModelRegistry;
      38: invokevirtual #250                // Method com/runanywhere/sdk/foundation/bridge/extensions/CppBridgeModelRegistry.scanAndRestoreDownloadedModels:()V
      41: invokestatic  #253                // Method syncRegisteredModelsWithBridge:()V
      44: iconst_1
      45: putstatic     #247                // Field hasScannedForDownloads:Z
      48: nop
      49: getstatic     #258                // Field kotlin/Unit.INSTANCE:Lkotlin/Unit;
      52: astore        4
      54: aload_3
      55: monitorexit
      56: goto          66
      59: astore        5
      61: aload_3
      62: monitorexit
      63: aload         5
      65: athrow
      66: invokestatic  #260                // Method getRegisteredModels:()Ljava/util/List;
      69: astore_2
      70: invokestatic  #262                // Method getAllBridgeModels:()Ljava/util/List;
      73: checkcast     #201                // class java/lang/Iterable
      76: astore        4
      78: iconst_0
      79: istore        5
      81: aload         4
      83: astore        6
      85: new           #264                // class java/util/ArrayList
      88: dup
      89: aload         4
      91: bipush        10
      93: invokestatic  #268                // Method kotlin/collections/CollectionsKt.collectionSizeOrDefault:(Ljava/lang/Iterable;I)I
      96: invokespecial #271                // Method java/util/ArrayList."<init>":(I)V
      99: checkcast     #273                // class java/util/Collection
     102: astore        7
     104: iconst_0
     105: istore        8
     107: aload         6
     109: invokeinterface #277,  1          // InterfaceMethod java/lang/Iterable.iterator:()Ljava/util/Iterator;
     114: astore        9
     116: aload         9
     118: invokeinterface #282,  1          // InterfaceMethod java/util/Iterator.hasNext:()Z
     123: ifeq          166
     126: aload         9
     128: invokeinterface #286,  1          // InterfaceMethod java/util/Iterator.next:()Ljava/lang/Object;
     133: astore        10
     135: aload         7
     137: aload         10
     139: checkcast     #11                 // class com/runanywhere/sdk/foundation/bridge/extensions/CppBridgeModelRegistry$ModelInfo
     142: astore        11
     144: astore        13
     146: iconst_0
     147: istore        12
     149: aload         11
     151: invokestatic  #288                // Method toPublicModelInfo:(Lcom/runanywhere/sdk/foundation/bridge/extensions/CppBridgeModelRegistry$ModelInfo;)Lcom/runanywhere/sdk/public/extensions/Models/ModelInfo;
     154: aload         13
     156: swap
     157: invokeinterface #289,  2          // InterfaceMethod java/util/Collection.add:(Ljava/lang/Object;)Z
     162: pop
     163: goto          116
     166: aload         7
     168: checkcast     #188                // class java/util/List
     171: nop
     172: astore_3
     173: new           #291                // class java/util/LinkedHashMap
     176: dup
     177: invokespecial #292                // Method java/util/LinkedHashMap."<init>":()V
     180: checkcast     #294                // class java/util/Map
     183: astore        4
     185: aload_3
     186: invokeinterface #295,  1          // InterfaceMethod java/util/List.iterator:()Ljava/util/Iterator;
     191: astore        5
     193: aload         5
     195: invokeinterface #282,  1          // InterfaceMethod java/util/Iterator.hasNext:()Z
     200: ifeq          233
     203: aload         5
     205: invokeinterface #286,  1          // InterfaceMethod java/util/Iterator.next:()Ljava/lang/Object;
     210: checkcast     #13                 // class com/runanywhere/sdk/public/extensions/Models/ModelInfo
     213: astore        6
     215: aload         4
     217: aload         6
     219: invokevirtual #17                 // Method com/runanywhere/sdk/public/extensions/Models/ModelInfo.getId:()Ljava/lang/String;
     222: aload         6
     224: invokeinterface #299,  3          // InterfaceMethod java/util/Map.put:(Ljava/lang/Object;Ljava/lang/Object;)Ljava/lang/Object;
     229: pop
     230: goto          193
     233: aload_2
     234: invokeinterface #295,  1          // InterfaceMethod java/util/List.iterator:()Ljava/util/Iterator;
     239: astore        5
     241: aload         5
     243: invokeinterface #282,  1          // InterfaceMethod java/util/Iterator.hasNext:()Z
     248: ifeq          281
     251: aload         5
     253: invokeinterface #286,  1          // InterfaceMethod java/util/Iterator.next:()Ljava/lang/Object;
     258: checkcast     #13                 // class com/runanywhere/sdk/public/extensions/Models/ModelInfo
     261: astore        6
     263: aload         4
     265: aload         6
     267: invokevirtual #17                 // Method com/runanywhere/sdk/public/extensions/Models/ModelInfo.getId:()Ljava/lang/String;
     270: aload         6
     272: invokeinterface #299,  3          // InterfaceMethod java/util/Map.put:(Ljava/lang/Object;Ljava/lang/Object;)Ljava/lang/Object;
     277: pop
     278: goto          241
     281: aload         4
     283: invokeinterface #303,  1          // InterfaceMethod java/util/Map.values:()Ljava/util/Collection;
     288: checkcast     #201                // class java/lang/Iterable
     291: invokestatic  #205                // Method kotlin/collections/CollectionsKt.toList:(Ljava/lang/Iterable;)Ljava/util/List;
     294: areturn
    Exception table:
       from    to  target type
          25    54    59   any
          59    61    59   any

  public static final java.lang.Object models(com.runanywhere.sdk.public.RunAnywhere, com.runanywhere.sdk.public.extensions.Models.ModelCategory, kotlin.coroutines.Continuation<? super java.util.List<com.runanywhere.sdk.public.extensions.Models.ModelInfo>>);
    Code:
       0: aload_0
       1: invokevirtual #226                // Method com/runanywhere/sdk/public/RunAnywhere.isInitialized:()Z
       4: ifne          19
       7: getstatic     #232                // Field com/runanywhere/sdk/foundation/errors/SDKError.Companion:Lcom/runanywhere/sdk/foundation/errors/SDKError$Companion;
      10: ldc           #234                // String SDK not initialized
      12: aconst_null
      13: iconst_2
      14: aconst_null
      15: invokestatic  #240                // Method com/runanywhere/sdk/foundation/errors/SDKError$Companion.notInitialized$default:(Lcom/runanywhere/sdk/foundation/errors/SDKError$Companion;Ljava/lang/String;Ljava/lang/Throwable;ILjava/lang/Object;)Lcom/runanywhere/sdk/foundation/errors/SDKError;
      18: athrow
      19: aload_1
      20: getstatic     #30                 // Field com/runanywhere/sdk/public/extensions/RunAnywhere_ModelManagement_jvmAndroidKt$WhenMappings.$EnumSwitchMapping$0:[I
      23: swap
      24: invokevirtual #36                 // Method com/runanywhere/sdk/public/extensions/Models/ModelCategory.ordinal:()I
      27: iaload
      28: tableswitch   { // 1 to 4

                     1: 60

                     2: 64

                     3: 68

                     4: 72
               default: 76
          }
      60: iconst_0
      61: goto          80
      64: iconst_1
      65: goto          80
      68: iconst_2
      69: goto          80
      72: iconst_3
      73: goto          80
      76: invokestatic  #352                // Method kotlin/collections/CollectionsKt.emptyList:()Ljava/util/List;
      79: areturn
      80: istore_3
      81: getstatic     #103                // Field com/runanywhere/sdk/foundation/bridge/extensions/CppBridgeModelRegistry.INSTANCE:Lcom/runanywhere/sdk/foundation/bridge/extensions/CppBridgeModelRegistry;
      84: iload_3
      85: invokevirtual #356                // Method com/runanywhere/sdk/foundation/bridge/extensions/CppBridgeModelRegistry.getModelsByType:(I)Ljava/util/List;
      88: checkcast     #201                // class java/lang/Iterable
      91: astore        4
      93: iconst_0
      94: istore        5
      96: aload         4
      98: astore        6
     100: new           #264                // class java/util/ArrayList
     103: dup
     104: aload         4
     106: bipush        10
     108: invokestatic  #268                // Method kotlin/collections/CollectionsKt.collectionSizeOrDefault:(Ljava/lang/Iterable;I)I
     111: invokespecial #271                // Method java/util/ArrayList."<init>":(I)V
     114: checkcast     #273                // class java/util/Collection
     117: astore        7
     119: iconst_0
     120: istore        8
     122: aload         6
     124: invokeinterface #277,  1          // InterfaceMethod java/lang/Iterable.iterator:()Ljava/util/Iterator;
     129: astore        9
     131: aload         9
     133: invokeinterface #282,  1          // InterfaceMethod java/util/Iterator.hasNext:()Z
     138: ifeq          181
     141: aload         9
     143: invokeinterface #286,  1          // InterfaceMethod java/util/Iterator.next:()Ljava/lang/Object;
     148: astore        10
     150: aload         7
     152: aload         10
     154: checkcast     #11                 // class com/runanywhere/sdk/foundation/bridge/extensions/CppBridgeModelRegistry$ModelInfo
     157: astore        11
     159: astore        13
     161: iconst_0
     162: istore        12
     164: aload         11
     166: invokestatic  #211                // Method bridgeModelToPublic:(Lcom/runanywhere/sdk/foundation/bridge/extensions/CppBridgeModelRegistry$ModelInfo;)Lcom/runanywhere/sdk/public/extensions/Models/ModelInfo;
     169: aload         13
     171: swap
     172: invokeinterface #289,  2          // InterfaceMethod java/util/Collection.add:(Ljava/lang/Object;)Z
     177: pop
     178: goto          131
     181: aload         7
     183: checkcast     #188                // class java/util/List
     186: nop
     187: areturn

  public static final java.lang.Object downloadedModels(com.runanywhere.sdk.public.RunAnywhere, kotlin.coroutines.Continuation<? super java.util.List<com.runanywhere.sdk.public.extensions.Models.ModelInfo>>);
    Code:
       0: aload_0
       1: invokevirtual #226                // Method com/runanywhere/sdk/public/RunAnywhere.isInitialized:()Z
       4: ifne          19
       7: getstatic     #232                // Field com/runanywhere/sdk/foundation/errors/SDKError.Companion:Lcom/runanywhere/sdk/foundation/errors/SDKError$Companion;
      10: ldc           #234                // String SDK not initialized
      12: aconst_null
      13: iconst_2
      14: aconst_null
      15: invokestatic  #240                // Method com/runanywhere/sdk/foundation/errors/SDKError$Companion.notInitialized$default:(Lcom/runanywhere/sdk/foundation/errors/SDKError$Companion;Ljava/lang/String;Ljava/lang/Throwable;ILjava/lang/Object;)Lcom/runanywhere/sdk/foundation/errors/SDKError;
      18: athrow
      19: getstatic     #103                // Field com/runanywhere/sdk/foundation/bridge/extensions/CppBridgeModelRegistry.INSTANCE:Lcom/runanywhere/sdk/foundation/bridge/extensions/CppBridgeModelRegistry;
      22: invokevirtual #365                // Method com/runanywhere/sdk/foundation/bridge/extensions/CppBridgeModelRegistry.getDownloaded:()Ljava/util/List;
      25: checkcast     #201                // class java/lang/Iterable
      28: astore_2
      29: iconst_0
      30: istore_3
      31: aload_2
      32: astore        4
      34: new           #264                // class java/util/ArrayList
      37: dup
      38: aload_2
      39: bipush        10
      41: invokestatic  #268                // Method kotlin/collections/CollectionsKt.collectionSizeOrDefault:(Ljava/lang/Iterable;I)I
      44: invokespecial #271                // Method java/util/ArrayList."<init>":(I)V
      47: checkcast     #273                // class java/util/Collection
      50: astore        5
      52: iconst_0
      53: istore        6
      55: aload         4
      57: invokeinterface #277,  1          // InterfaceMethod java/lang/Iterable.iterator:()Ljava/util/Iterator;
      62: astore        7
      64: aload         7
      66: invokeinterface #282,  1          // InterfaceMethod java/util/Iterator.hasNext:()Z
      71: ifeq          114
      74: aload         7
      76: invokeinterface #286,  1          // InterfaceMethod java/util/Iterator.next:()Ljava/lang/Object;
      81: astore        8
      83: aload         5
      85: aload         8
      87: checkcast     #11                 // class com/runanywhere/sdk/foundation/bridge/extensions/CppBridgeModelRegistry$ModelInfo
      90: astore        9
      92: astore        11
      94: iconst_0
      95: istore        10
      97: aload         9
      99: invokestatic  #211                // Method bridgeModelToPublic:(Lcom/runanywhere/sdk/foundation/bridge/extensions/CppBridgeModelRegistry$ModelInfo;)Lcom/runanywhere/sdk/public/extensions/Models/ModelInfo;
     102: aload         11
     104: swap
     105: invokeinterface #289,  2          // InterfaceMethod java/util/Collection.add:(Ljava/lang/Object;)Z
     110: pop
     111: goto          64
     114: aload         5
     116: checkcast     #188                // class java/util/List
     119: nop
     120: areturn

  public static final java.lang.Object model(com.runanywhere.sdk.public.RunAnywhere, java.lang.String, kotlin.coroutines.Continuation<? super com.runanywhere.sdk.public.extensions.Models.ModelInfo>);
    Code:
       0: aload_0
       1: invokevirtual #226                // Method com/runanywhere/sdk/public/RunAnywhere.isInitialized:()Z
       4: ifne          19
       7: getstatic     #232                // Field com/runanywhere/sdk/foundation/errors/SDKError.Companion:Lcom/runanywhere/sdk/foundation/errors/SDKError$Companion;
      10: ldc           #234                // String SDK not initialized
      12: aconst_null
      13: iconst_2
      14: aconst_null
      15: invokestatic  #240                // Method com/runanywhere/sdk/foundation/errors/SDKError$Companion.notInitialized$default:(Lcom/runanywhere/sdk/foundation/errors/SDKError$Companion;Ljava/lang/String;Ljava/lang/Throwable;ILjava/lang/Object;)Lcom/runanywhere/sdk/foundation/errors/SDKError;
      18: athrow
      19: getstatic     #103                // Field com/runanywhere/sdk/foundation/bridge/extensions/CppBridgeModelRegistry.INSTANCE:Lcom/runanywhere/sdk/foundation/bridge/extensions/CppBridgeModelRegistry;
      22: aload_1
      23: invokevirtual #330                // Method com/runanywhere/sdk/foundation/bridge/extensions/CppBridgeModelRegistry.get:(Ljava/lang/String;)Lcom/runanywhere/sdk/foundation/bridge/extensions/CppBridgeModelRegistry$ModelInfo;
      26: dup
      27: ifnonnull     33
      30: pop
      31: aconst_null
      32: areturn
      33: astore_3
      34: aload_3
      35: invokestatic  #211                // Method bridgeModelToPublic:(Lcom/runanywhere/sdk/foundation/bridge/extensions/CppBridgeModelRegistry$ModelInfo;)Lcom/runanywhere/sdk/public/extensions/Models/ModelInfo;
      38: areturn

  public static final kotlinx.coroutines.flow.Flow<com.runanywhere.sdk.public.extensions.Models.DownloadProgress> downloadModel(com.runanywhere.sdk.public.RunAnywhere, java.lang.String);
    Code:
       0: new           #447                // class com/runanywhere/sdk/public/extensions/RunAnywhere_ModelManagement_jvmAndroidKt$downloadModel$1
       3: dup
       4: aload_1
       5: aconst_null
       6: invokespecial #450                // Method com/runanywhere/sdk/public/extensions/RunAnywhere_ModelManagement_jvmAndroidKt$downloadModel$1."<init>":(Ljava/lang/String;Lkotlin/coroutines/Continuation;)V
       9: checkcast     #452                // class kotlin/jvm/functions/Function2
      12: invokestatic  #458                // Method kotlinx/coroutines/flow/FlowKt.callbackFlow:(Lkotlin/jvm/functions/Function2;)Lkotlinx/coroutines/flow/Flow;
      15: areturn

  public static final java.lang.Object cancelDownload(com.runanywhere.sdk.public.RunAnywhere, java.lang.String, kotlin.coroutines.Continuation<? super kotlin.Unit>);
    Code:
       0: aload_0
       1: invokevirtual #226                // Method com/runanywhere/sdk/public/RunAnywhere.isInitialized:()Z
       4: ifne          19
       7: getstatic     #232                // Field com/runanywhere/sdk/foundation/errors/SDKError.Companion:Lcom/runanywhere/sdk/foundation/errors/SDKError$Companion;
      10: ldc           #234                // String SDK not initialized
      12: aconst_null
      13: iconst_2
      14: aconst_null
      15: invokestatic  #240                // Method com/runanywhere/sdk/foundation/errors/SDKError$Companion.notInitialized$default:(Lcom/runanywhere/sdk/foundation/errors/SDKError$Companion;Ljava/lang/String;Ljava/lang/Throwable;ILjava/lang/Object;)Lcom/runanywhere/sdk/foundation/errors/SDKError;
      18: athrow
      19: getstatic     #103                // Field com/runanywhere/sdk/foundation/bridge/extensions/CppBridgeModelRegistry.INSTANCE:Lcom/runanywhere/sdk/foundation/bridge/extensions/CppBridgeModelRegistry;
      22: aload_1
      23: aconst_null
      24: invokevirtual #717                // Method com/runanywhere/sdk/foundation/bridge/extensions/CppBridgeModelRegistry.updateDownloadStatus:(Ljava/lang/String;Ljava/lang/String;)Z
      27: pop
      28: getstatic     #258                // Field kotlin/Unit.INSTANCE:Lkotlin/Unit;
      31: areturn

  public static final java.lang.Object isModelDownloaded(com.runanywhere.sdk.public.RunAnywhere, java.lang.String, kotlin.coroutines.Continuation<? super java.lang.Boolean>);
    Code:
       0: aload_0
       1: invokevirtual #226                // Method com/runanywhere/sdk/public/RunAnywhere.isInitialized:()Z
       4: ifne          19
       7: getstatic     #232                // Field com/runanywhere/sdk/foundation/errors/SDKError.Companion:Lcom/runanywhere/sdk/foundation/errors/SDKError$Companion;
      10: ldc           #234                // String SDK not initialized
      12: aconst_null
      13: iconst_2
      14: aconst_null
      15: invokestatic  #240                // Method com/runanywhere/sdk/foundation/errors/SDKError$Companion.notInitialized$default:(Lcom/runanywhere/sdk/foundation/errors/SDKError$Companion;Ljava/lang/String;Ljava/lang/Throwable;ILjava/lang/Object;)Lcom/runanywhere/sdk/foundation/errors/SDKError;
      18: athrow
      19: getstatic     #103                // Field com/runanywhere/sdk/foundation/bridge/extensions/CppBridgeModelRegistry.INSTANCE:Lcom/runanywhere/sdk/foundation/bridge/extensions/CppBridgeModelRegistry;
      22: aload_1
      23: invokevirtual #330                // Method com/runanywhere/sdk/foundation/bridge/extensions/CppBridgeModelRegistry.get:(Ljava/lang/String;)Lcom/runanywhere/sdk/foundation/bridge/extensions/CppBridgeModelRegistry$ModelInfo;
      26: dup
      27: ifnonnull     36
      30: pop
      31: iconst_0
      32: invokestatic  #726                // Method kotlin/coroutines/jvm/internal/Boxing.boxBoolean:(Z)Ljava/lang/Boolean;
      35: areturn
      36: astore_3
      37: aload_3
      38: invokevirtual #331                // Method com/runanywhere/sdk/foundation/bridge/extensions/CppBridgeModelRegistry$ModelInfo.getLocalPath:()Ljava/lang/String;
      41: ifnull        71
      44: aload_3
      45: invokevirtual #331                // Method com/runanywhere/sdk/foundation/bridge/extensions/CppBridgeModelRegistry$ModelInfo.getLocalPath:()Ljava/lang/String;
      48: checkcast     #728                // class java/lang/CharSequence
      51: invokeinterface #731,  1          // InterfaceMethod java/lang/CharSequence.length:()I
      56: ifle          63
      59: iconst_1
      60: goto          64
      63: iconst_0
      64: ifeq          71
      67: iconst_1
      68: goto          72
      71: iconst_0
      72: invokestatic  #726                // Method kotlin/coroutines/jvm/internal/Boxing.boxBoolean:(Z)Ljava/lang/Boolean;
      75: areturn

  public static final java.lang.Object deleteModel(com.runanywhere.sdk.public.RunAnywhere, java.lang.String, kotlin.coroutines.Continuation<? super kotlin.Unit>);
    Code:
       0: aload_0
       1: invokevirtual #226                // Method com/runanywhere/sdk/public/RunAnywhere.isInitialized:()Z
       4: ifne          19
       7: getstatic     #232                // Field com/runanywhere/sdk/foundation/errors/SDKError.Companion:Lcom/runanywhere/sdk/foundation/errors/SDKError$Companion;
      10: ldc           #234                // String SDK not initialized
      12: aconst_null
      13: iconst_2
      14: aconst_null
      15: invokestatic  #240                // Method com/runanywhere/sdk/foundation/errors/SDKError$Companion.notInitialized$default:(Lcom/runanywhere/sdk/foundation/errors/SDKError$Companion;Ljava/lang/String;Ljava/lang/Throwable;ILjava/lang/Object;)Lcom/runanywhere/sdk/foundation/errors/SDKError;
      18: athrow
      19: getstatic     #103                // Field com/runanywhere/sdk/foundation/bridge/extensions/CppBridgeModelRegistry.INSTANCE:Lcom/runanywhere/sdk/foundation/bridge/extensions/CppBridgeModelRegistry;
      22: aload_1
      23: invokevirtual #736                // Method com/runanywhere/sdk/foundation/bridge/extensions/CppBridgeModelRegistry.remove:(Ljava/lang/String;)Z
      26: pop
      27: getstatic     #258                // Field kotlin/Unit.INSTANCE:Lkotlin/Unit;
      30: areturn

  public static final java.lang.Object deleteAllModels(com.runanywhere.sdk.public.RunAnywhere, kotlin.coroutines.Continuation<? super kotlin.Unit>);
    Code:
       0: aload_0
       1: invokevirtual #226                // Method com/runanywhere/sdk/public/RunAnywhere.isInitialized:()Z
       4: ifne          19
       7: getstatic     #232                // Field com/runanywhere/sdk/foundation/errors/SDKError.Companion:Lcom/runanywhere/sdk/foundation/errors/SDKError$Companion;
      10: ldc           #234                // String SDK not initialized
      12: aconst_null
      13: iconst_2
      14: aconst_null
      15: invokestatic  #240                // Method com/runanywhere/sdk/foundation/errors/SDKError$Companion.notInitialized$default:(Lcom/runanywhere/sdk/foundation/errors/SDKError$Companion;Ljava/lang/String;Ljava/lang/Throwable;ILjava/lang/Object;)Lcom/runanywhere/sdk/foundation/errors/SDKError;
      18: athrow
      19: getstatic     #258                // Field kotlin/Unit.INSTANCE:Lkotlin/Unit;
      22: areturn

  public static final java.lang.Object refreshModelRegistry(com.runanywhere.sdk.public.RunAnywhere, kotlin.coroutines.Continuation<? super kotlin.Unit>);
    Code:
       0: aload_0
       1: invokevirtual #226                // Method com/runanywhere/sdk/public/RunAnywhere.isInitialized:()Z
       4: ifne          19
       7: getstatic     #232                // Field com/runanywhere/sdk/foundation/errors/SDKError.Companion:Lcom/runanywhere/sdk/foundation/errors/SDKError$Companion;
      10: ldc           #234                // String SDK not initialized
      12: aconst_null
      13: iconst_2
      14: aconst_null
      15: invokestatic  #240                // Method com/runanywhere/sdk/foundation/errors/SDKError$Companion.notInitialized$default:(Lcom/runanywhere/sdk/foundation/errors/SDKError$Companion;Ljava/lang/String;Ljava/lang/Throwable;ILjava/lang/Object;)Lcom/runanywhere/sdk/foundation/errors/SDKError;
      18: athrow
      19: getstatic     #258                // Field kotlin/Unit.INSTANCE:Lkotlin/Unit;
      22: areturn

  public static final java.lang.Object loadLLMModel(com.runanywhere.sdk.public.RunAnywhere, java.lang.String, kotlin.coroutines.Continuation<? super kotlin.Unit>);
    Code:
       0: aload_0
       1: invokevirtual #226                // Method com/runanywhere/sdk/public/RunAnywhere.isInitialized:()Z
       4: ifne          19
       7: getstatic     #232                // Field com/runanywhere/sdk/foundation/errors/SDKError.Companion:Lcom/runanywhere/sdk/foundation/errors/SDKError$Companion;
      10: ldc           #234                // String SDK not initialized
      12: aconst_null
      13: iconst_2
      14: aconst_null
      15: invokestatic  #240                // Method com/runanywhere/sdk/foundation/errors/SDKError$Companion.notInitialized$default:(Lcom/runanywhere/sdk/foundation/errors/SDKError$Companion;Ljava/lang/String;Ljava/lang/Throwable;ILjava/lang/Object;)Lcom/runanywhere/sdk/foundation/errors/SDKError;
      18: athrow
      19: getstatic     #103                // Field com/runanywhere/sdk/foundation/bridge/extensions/CppBridgeModelRegistry.INSTANCE:Lcom/runanywhere/sdk/foundation/bridge/extensions/CppBridgeModelRegistry;
      22: aload_1
      23: invokevirtual #330                // Method com/runanywhere/sdk/foundation/bridge/extensions/CppBridgeModelRegistry.get:(Ljava/lang/String;)Lcom/runanywhere/sdk/foundation/bridge/extensions/CppBridgeModelRegistry$ModelInfo;
      26: dup
      27: ifnonnull     49
      30: pop
      31: getstatic     #232                // Field com/runanywhere/sdk/foundation/errors/SDKError.Companion:Lcom/runanywhere/sdk/foundation/errors/SDKError$Companion;
      34: aload_1
      35: invokedynamic #746,  0            // InvokeDynamic #11:makeConcatWithConstants:(Ljava/lang/String;)Ljava/lang/String;
      40: aconst_null
      41: aconst_null
      42: bipush        6
      44: aconst_null
      45: invokestatic  #750                // Method com/runanywhere/sdk/foundation/errors/SDKError$Companion.model$default:(Lcom/runanywhere/sdk/foundation/errors/SDKError$Companion;Ljava/lang/String;Lcom/runanywhere/sdk/foundation/errors/ErrorCode;Ljava/lang/Throwable;ILjava/lang/Object;)Lcom/runanywhere/sdk/foundation/errors/SDKError;
      48: athrow
      49: astore_3
      50: aload_3
      51: invokevirtual #331                // Method com/runanywhere/sdk/foundation/bridge/extensions/CppBridgeModelRegistry$ModelInfo.getLocalPath:()Ljava/lang/String;
      54: dup
      55: ifnonnull     77
      58: pop
      59: getstatic     #232                // Field com/runanywhere/sdk/foundation/errors/SDKError.Companion:Lcom/runanywhere/sdk/foundation/errors/SDKError$Companion;
      62: aload_1
      63: invokedynamic #753,  0            // InvokeDynamic #12:makeConcatWithConstants:(Ljava/lang/String;)Ljava/lang/String;
      68: aconst_null
      69: aconst_null
      70: bipush        6
      72: aconst_null
      73: invokestatic  #750                // Method com/runanywhere/sdk/foundation/errors/SDKError$Companion.model$default:(Lcom/runanywhere/sdk/foundation/errors/SDKError$Companion;Ljava/lang/String;Lcom/runanywhere/sdk/foundation/errors/ErrorCode;Ljava/lang/Throwable;ILjava/lang/Object;)Lcom/runanywhere/sdk/foundation/errors/SDKError;
      76: athrow
      77: astore        4
      79: getstatic     #758                // Field com/runanywhere/sdk/foundation/bridge/extensions/CppBridgeLLM.INSTANCE:Lcom/runanywhere/sdk/foundation/bridge/extensions/CppBridgeLLM;
      82: aload         4
      84: aload_1
      85: aload_3
      86: invokevirtual #376                // Method com/runanywhere/sdk/foundation/bridge/extensions/CppBridgeModelRegistry$ModelInfo.getName:()Ljava/lang/String;
      89: aconst_null
      90: bipush        8
      92: aconst_null
      93: invokestatic  #762                // Method com/runanywhere/sdk/foundation/bridge/extensions/CppBridgeLLM.loadModel$default:(Lcom/runanywhere/sdk/foundation/bridge/extensions/CppBridgeLLM;Ljava/lang/String;Ljava/lang/String;Ljava/lang/String;Lcom/runanywhere/sdk/foundation/bridge/extensions/CppBridgeLLM$ModelConfig;ILjava/lang/Object;)I
      96: istore        5
      98: iload         5
     100: ifeq          123
     103: getstatic     #232                // Field com/runanywhere/sdk/foundation/errors/SDKError.Companion:Lcom/runanywhere/sdk/foundation/errors/SDKError$Companion;
     106: aload_1
     107: iload         5
     109: invokedynamic #767,  0            // InvokeDynamic #13:makeConcatWithConstants:(Ljava/lang/String;I)Ljava/lang/String;
     114: aconst_null
     115: aconst_null
     116: bipush        6
     118: aconst_null
     119: invokestatic  #770                // Method com/runanywhere/sdk/foundation/errors/SDKError$Companion.llm$default:(Lcom/runanywhere/sdk/foundation/errors/SDKError$Companion;Ljava/lang/String;Lcom/runanywhere/sdk/foundation/errors/ErrorCode;Ljava/lang/Throwable;ILjava/lang/Object;)Lcom/runanywhere/sdk/foundation/errors/SDKError;
     122: athrow
     123: getstatic     #258                // Field kotlin/Unit.INSTANCE:Lkotlin/Unit;
     126: areturn

  public static final java.lang.Object unloadLLMModel(com.runanywhere.sdk.public.RunAnywhere, kotlin.coroutines.Continuation<? super kotlin.Unit>);
    Code:
       0: aload_0
       1: invokevirtual #226                // Method com/runanywhere/sdk/public/RunAnywhere.isInitialized:()Z
       4: ifne          19
       7: getstatic     #232                // Field com/runanywhere/sdk/foundation/errors/SDKError.Companion:Lcom/runanywhere/sdk/foundation/errors/SDKError$Companion;
      10: ldc           #234                // String SDK not initialized
      12: aconst_null
      13: iconst_2
      14: aconst_null
      15: invokestatic  #240                // Method com/runanywhere/sdk/foundation/errors/SDKError$Companion.notInitialized$default:(Lcom/runanywhere/sdk/foundation/errors/SDKError$Companion;Ljava/lang/String;Ljava/lang/Throwable;ILjava/lang/Object;)Lcom/runanywhere/sdk/foundation/errors/SDKError;
      18: athrow
      19: getstatic     #758                // Field com/runanywhere/sdk/foundation/bridge/extensions/CppBridgeLLM.INSTANCE:Lcom/runanywhere/sdk/foundation/bridge/extensions/CppBridgeLLM;
      22: invokevirtual #776                // Method com/runanywhere/sdk/foundation/bridge/extensions/CppBridgeLLM.unload:()V
      25: getstatic     #258                // Field kotlin/Unit.INSTANCE:Lkotlin/Unit;
      28: areturn

  public static final java.lang.Object isLLMModelLoaded(com.runanywhere.sdk.public.RunAnywhere, kotlin.coroutines.Continuation<? super java.lang.Boolean>);
    Code:
       0: getstatic     #758                // Field com/runanywhere/sdk/foundation/bridge/extensions/CppBridgeLLM.INSTANCE:Lcom/runanywhere/sdk/foundation/bridge/extensions/CppBridgeLLM;
       3: invokevirtual #782                // Method com/runanywhere/sdk/foundation/bridge/extensions/CppBridgeLLM.isLoaded:()Z
       6: invokestatic  #726                // Method kotlin/coroutines/jvm/internal/Boxing.boxBoolean:(Z)Ljava/lang/Boolean;
       9: areturn

  public static final java.lang.String getCurrentLLMModelId(com.runanywhere.sdk.public.RunAnywhere);
    Code:
       0: getstatic     #758                // Field com/runanywhere/sdk/foundation/bridge/extensions/CppBridgeLLM.INSTANCE:Lcom/runanywhere/sdk/foundation/bridge/extensions/CppBridgeLLM;
       3: invokevirtual #788                // Method com/runanywhere/sdk/foundation/bridge/extensions/CppBridgeLLM.getLoadedModelId:()Ljava/lang/String;
       6: areturn

  public static final java.lang.Object currentLLMModel(com.runanywhere.sdk.public.RunAnywhere, kotlin.coroutines.Continuation<? super com.runanywhere.sdk.public.extensions.Models.ModelInfo>);
    Code:
       0: getstatic     #758                // Field com/runanywhere/sdk/foundation/bridge/extensions/CppBridgeLLM.INSTANCE:Lcom/runanywhere/sdk/foundation/bridge/extensions/CppBridgeLLM;
       3: invokevirtual #788                // Method com/runanywhere/sdk/foundation/bridge/extensions/CppBridgeLLM.getLoadedModelId:()Ljava/lang/String;
       6: dup
       7: ifnonnull     13
      10: pop
      11: aconst_null
      12: areturn
      13: astore_2
      14: invokestatic  #260                // Method getRegisteredModels:()Ljava/util/List;
      17: checkcast     #201                // class java/lang/Iterable
      20: astore        4
      22: aload         4
      24: invokeinterface #277,  1          // InterfaceMethod java/lang/Iterable.iterator:()Ljava/util/Iterator;
      29: astore        5
      31: aload         5
      33: invokeinterface #282,  1          // InterfaceMethod java/util/Iterator.hasNext:()Z
      38: ifeq          77
      41: aload         5
      43: invokeinterface #286,  1          // InterfaceMethod java/util/Iterator.next:()Ljava/lang/Object;
      48: astore        6
      50: aload         6
      52: checkcast     #13                 // class com/runanywhere/sdk/public/extensions/Models/ModelInfo
      55: astore        7
      57: iconst_0
      58: istore        8
      60: aload         7
      62: invokevirtual #17                 // Method com/runanywhere/sdk/public/extensions/Models/ModelInfo.getId:()Ljava/lang/String;
      65: aload_2
      66: invokestatic  #795                // Method kotlin/jvm/internal/Intrinsics.areEqual:(Ljava/lang/Object;Ljava/lang/Object;)Z
      69: ifeq          31
      72: aload         6
      74: goto          78
      77: aconst_null
      78: checkcast     #13                 // class com/runanywhere/sdk/public/extensions/Models/ModelInfo
      81: astore_3
      82: aload_3
      83: dup
      84: ifnull        88
      87: areturn
      88: pop
      89: invokestatic  #262                // Method getAllBridgeModels:()Ljava/util/List;
      92: checkcast     #201                // class java/lang/Iterable
      95: astore        5
      97: aload         5
      99: invokeinterface #277,  1          // InterfaceMethod java/lang/Iterable.iterator:()Ljava/util/Iterator;
     104: astore        6
     106: aload         6
     108: invokeinterface #282,  1          // InterfaceMethod java/util/Iterator.hasNext:()Z
     113: ifeq          152
     116: aload         6
     118: invokeinterface #286,  1          // InterfaceMethod java/util/Iterator.next:()Ljava/lang/Object;
     123: astore        7
     125: aload         7
     127: checkcast     #11                 // class com/runanywhere/sdk/foundation/bridge/extensions/CppBridgeModelRegistry$ModelInfo
     130: astore        8
     132: iconst_0
     133: istore        9
     135: aload         8
     137: invokevirtual #375                // Method com/runanywhere/sdk/foundation/bridge/extensions/CppBridgeModelRegistry$ModelInfo.getModelId:()Ljava/lang/String;
     140: aload_2
     141: invokestatic  #795                // Method kotlin/jvm/internal/Intrinsics.areEqual:(Ljava/lang/Object;Ljava/lang/Object;)Z
     144: ifeq          106
     147: aload         7
     149: goto          153
     152: aconst_null
     153: checkcast     #11                 // class com/runanywhere/sdk/foundation/bridge/extensions/CppBridgeModelRegistry$ModelInfo
     156: dup
     157: ifnull        166
     160: invokestatic  #288                // Method toPublicModelInfo:(Lcom/runanywhere/sdk/foundation/bridge/extensions/CppBridgeModelRegistry$ModelInfo;)Lcom/runanywhere/sdk/public/extensions/Models/ModelInfo;
     163: goto          168
     166: pop
     167: aconst_null
     168: areturn

  public static final java.lang.Object currentSTTModel(com.runanywhere.sdk.public.RunAnywhere, kotlin.coroutines.Continuation<? super com.runanywhere.sdk.public.extensions.Models.ModelInfo>);
    Code:
       0: getstatic     #805                // Field com/runanywhere/sdk/foundation/bridge/extensions/CppBridgeSTT.INSTANCE:Lcom/runanywhere/sdk/foundation/bridge/extensions/CppBridgeSTT;
       3: invokevirtual #806                // Method com/runanywhere/sdk/foundation/bridge/extensions/CppBridgeSTT.getLoadedModelId:()Ljava/lang/String;
       6: dup
       7: ifnonnull     13
      10: pop
      11: aconst_null
      12: areturn
      13: astore_2
      14: invokestatic  #260                // Method getRegisteredModels:()Ljava/util/List;
      17: checkcast     #201                // class java/lang/Iterable
      20: astore        4
      22: aload         4
      24: invokeinterface #277,  1          // InterfaceMethod java/lang/Iterable.iterator:()Ljava/util/Iterator;
      29: astore        5
      31: aload         5
      33: invokeinterface #282,  1          // InterfaceMethod java/util/Iterator.hasNext:()Z
      38: ifeq          77
      41: aload         5
      43: invokeinterface #286,  1          // InterfaceMethod java/util/Iterator.next:()Ljava/lang/Object;
      48: astore        6
      50: aload         6
      52: checkcast     #13                 // class com/runanywhere/sdk/public/extensions/Models/ModelInfo
      55: astore        7
      57: iconst_0
      58: istore        8
      60: aload         7
      62: invokevirtual #17                 // Method com/runanywhere/sdk/public/extensions/Models/ModelInfo.getId:()Ljava/lang/String;
      65: aload_2
      66: invokestatic  #795                // Method kotlin/jvm/internal/Intrinsics.areEqual:(Ljava/lang/Object;Ljava/lang/Object;)Z
      69: ifeq          31
      72: aload         6
      74: goto          78
      77: aconst_null
      78: checkcast     #13                 // class com/runanywhere/sdk/public/extensions/Models/ModelInfo
      81: astore_3
      82: aload_3
      83: dup
      84: ifnull        88
      87: areturn
      88: pop
      89: invokestatic  #262                // Method getAllBridgeModels:()Ljava/util/List;
      92: checkcast     #201                // class java/lang/Iterable
      95: astore        5
      97: aload         5
      99: invokeinterface #277,  1          // InterfaceMethod java/lang/Iterable.iterator:()Ljava/util/Iterator;
     104: astore        6
     106: aload         6
     108: invokeinterface #282,  1          // InterfaceMethod java/util/Iterator.hasNext:()Z
     113: ifeq          152
     116: aload         6
     118: invokeinterface #286,  1          // InterfaceMethod java/util/Iterator.next:()Ljava/lang/Object;
     123: astore        7
     125: aload         7
     127: checkcast     #11                 // class com/runanywhere/sdk/foundation/bridge/extensions/CppBridgeModelRegistry$ModelInfo
     130: astore        8
     132: iconst_0
     133: istore        9
     135: aload         8
     137: invokevirtual #375                // Method com/runanywhere/sdk/foundation/bridge/extensions/CppBridgeModelRegistry$ModelInfo.getModelId:()Ljava/lang/String;
     140: aload_2
     141: invokestatic  #795                // Method kotlin/jvm/internal/Intrinsics.areEqual:(Ljava/lang/Object;Ljava/lang/Object;)Z
     144: ifeq          106
     147: aload         7
     149: goto          153
     152: aconst_null
     153: checkcast     #11                 // class com/runanywhere/sdk/foundation/bridge/extensions/CppBridgeModelRegistry$ModelInfo
     156: dup
     157: ifnull        166
     160: invokestatic  #288                // Method toPublicModelInfo:(Lcom/runanywhere/sdk/foundation/bridge/extensions/CppBridgeModelRegistry$ModelInfo;)Lcom/runanywhere/sdk/public/extensions/Models/ModelInfo;
     163: goto          168
     166: pop
     167: aconst_null
     168: areturn

  public static final java.lang.Object loadSTTModel(com.runanywhere.sdk.public.RunAnywhere, java.lang.String, kotlin.coroutines.Continuation<? super kotlin.Unit>);
    Code:
       0: aload_0
       1: invokevirtual #226                // Method com/runanywhere/sdk/public/RunAnywhere.isInitialized:()Z
       4: ifne          19
       7: getstatic     #232                // Field com/runanywhere/sdk/foundation/errors/SDKError.Companion:Lcom/runanywhere/sdk/foundation/errors/SDKError$Companion;
      10: ldc           #234                // String SDK not initialized
      12: aconst_null
      13: iconst_2
      14: aconst_null
      15: invokestatic  #240                // Method com/runanywhere/sdk/foundation/errors/SDKError$Companion.notInitialized$default:(Lcom/runanywhere/sdk/foundation/errors/SDKError$Companion;Ljava/lang/String;Ljava/lang/Throwable;ILjava/lang/Object;)Lcom/runanywhere/sdk/foundation/errors/SDKError;
      18: athrow
      19: getstatic     #103                // Field com/runanywhere/sdk/foundation/bridge/extensions/CppBridgeModelRegistry.INSTANCE:Lcom/runanywhere/sdk/foundation/bridge/extensions/CppBridgeModelRegistry;
      22: aload_1
      23: invokevirtual #330                // Method com/runanywhere/sdk/foundation/bridge/extensions/CppBridgeModelRegistry.get:(Ljava/lang/String;)Lcom/runanywhere/sdk/foundation/bridge/extensions/CppBridgeModelRegistry$ModelInfo;
      26: dup
      27: ifnonnull     49
      30: pop
      31: getstatic     #232                // Field com/runanywhere/sdk/foundation/errors/SDKError.Companion:Lcom/runanywhere/sdk/foundation/errors/SDKError$Companion;
      34: aload_1
      35: invokedynamic #746,  0            // InvokeDynamic #11:makeConcatWithConstants:(Ljava/lang/String;)Ljava/lang/String;
      40: aconst_null
      41: aconst_null
      42: bipush        6
      44: aconst_null
      45: invokestatic  #750                // Method com/runanywhere/sdk/foundation/errors/SDKError$Companion.model$default:(Lcom/runanywhere/sdk/foundation/errors/SDKError$Companion;Ljava/lang/String;Lcom/runanywhere/sdk/foundation/errors/ErrorCode;Ljava/lang/Throwable;ILjava/lang/Object;)Lcom/runanywhere/sdk/foundation/errors/SDKError;
      48: athrow
      49: astore_3
      50: aload_3
      51: invokevirtual #331                // Method com/runanywhere/sdk/foundation/bridge/extensions/CppBridgeModelRegistry$ModelInfo.getLocalPath:()Ljava/lang/String;
      54: dup
      55: ifnonnull     77
      58: pop
      59: getstatic     #232                // Field com/runanywhere/sdk/foundation/errors/SDKError.Companion:Lcom/runanywhere/sdk/foundation/errors/SDKError$Companion;
      62: aload_1
      63: invokedynamic #753,  0            // InvokeDynamic #12:makeConcatWithConstants:(Ljava/lang/String;)Ljava/lang/String;
      68: aconst_null
      69: aconst_null
      70: bipush        6
      72: aconst_null
      73: invokestatic  #750                // Method com/runanywhere/sdk/foundation/errors/SDKError$Companion.model$default:(Lcom/runanywhere/sdk/foundation/errors/SDKError$Companion;Ljava/lang/String;Lcom/runanywhere/sdk/foundation/errors/ErrorCode;Ljava/lang/Throwable;ILjava/lang/Object;)Lcom/runanywhere/sdk/foundation/errors/SDKError;
      76: athrow
      77: astore        4
      79: getstatic     #805                // Field com/runanywhere/sdk/foundation/bridge/extensions/CppBridgeSTT.INSTANCE:Lcom/runanywhere/sdk/foundation/bridge/extensions/CppBridgeSTT;
      82: aload         4
      84: aload_1
      85: aload_3
      86: invokevirtual #376                // Method com/runanywhere/sdk/foundation/bridge/extensions/CppBridgeModelRegistry$ModelInfo.getName:()Ljava/lang/String;
      89: aconst_null
      90: bipush        8
      92: aconst_null
      93: invokestatic  #813                // Method com/runanywhere/sdk/foundation/bridge/extensions/CppBridgeSTT.loadModel$default:(Lcom/runanywhere/sdk/foundation/bridge/extensions/CppBridgeSTT;Ljava/lang/String;Ljava/lang/String;Ljava/lang/String;Lcom/runanywhere/sdk/foundation/bridge/extensions/CppBridgeSTT$ModelConfig;ILjava/lang/Object;)I
      96: istore        5
      98: iload         5
     100: ifeq          123
     103: getstatic     #232                // Field com/runanywhere/sdk/foundation/errors/SDKError.Companion:Lcom/runanywhere/sdk/foundation/errors/SDKError$Companion;
     106: aload_1
     107: iload         5
     109: invokedynamic #816,  0            // InvokeDynamic #14:makeConcatWithConstants:(Ljava/lang/String;I)Ljava/lang/String;
     114: aconst_null
     115: aconst_null
     116: bipush        6
     118: aconst_null
     119: invokestatic  #819                // Method com/runanywhere/sdk/foundation/errors/SDKError$Companion.stt$default:(Lcom/runanywhere/sdk/foundation/errors/SDKError$Companion;Ljava/lang/String;Lcom/runanywhere/sdk/foundation/errors/ErrorCode;Ljava/lang/Throwable;ILjava/lang/Object;)Lcom/runanywhere/sdk/foundation/errors/SDKError;
     122: athrow
     123: getstatic     #258                // Field kotlin/Unit.INSTANCE:Lkotlin/Unit;
     126: areturn

  public static final java.util.List access$getRegisteredModels();
    Code:
       0: invokestatic  #260                // Method getRegisteredModels:()Ljava/util/List;
       3: areturn

  public static final boolean access$requiresExtraction(java.lang.String);
    Code:
       0: aload_0
       1: invokestatic  #825                // Method requiresExtraction:(Ljava/lang/String;)Z
       4: ireturn

  public static final java.lang.Object access$extractArchive(java.io.File, java.lang.String, int, java.lang.String, com.runanywhere.sdk.foundation.SDKLogger, kotlin.coroutines.Continuation);
    Code:
       0: aload_0
       1: aload_1
       2: iload_2
       3: aload_3
       4: aload         4
       6: aload         5
       8: invokestatic  #828                // Method extractArchive:(Ljava/io/File;Ljava/lang/String;ILjava/lang/String;Lcom/runanywhere/sdk/foundation/SDKLogger;Lkotlin/coroutines/Continuation;)Ljava/lang/Object;
      11: areturn

  public static final void access$addToModelCache(com.runanywhere.sdk.public.extensions.Models.ModelInfo);
    Code:
       0: aload_0
       1: invokestatic  #110                // Method addToModelCache:(Lcom/runanywhere/sdk/public/extensions/Models/ModelInfo;)V
       4: return

  public static final void access$extractTarGz(java.io.File, java.io.File, com.runanywhere.sdk.foundation.SDKLogger);
    Code:
       0: aload_0
       1: aload_1
       2: aload_2
       3: invokestatic  #833                // Method extractTarGz:(Ljava/io/File;Ljava/io/File;Lcom/runanywhere/sdk/foundation/SDKLogger;)V
       6: return

  public static final void access$extractTarBz2(java.io.File, java.io.File, com.runanywhere.sdk.foundation.SDKLogger);
    Code:
       0: aload_0
       1: aload_1
       2: aload_2
       3: invokestatic  #836                // Method extractTarBz2:(Ljava/io/File;Ljava/io/File;Lcom/runanywhere/sdk/foundation/SDKLogger;)V
       6: return

  public static final void access$extractZip(java.io.File, java.io.File, com.runanywhere.sdk.foundation.SDKLogger);
    Code:
       0: aload_0
       1: aload_1
       2: aload_2
       3: invokestatic  #839                // Method extractZip:(Ljava/io/File;Ljava/io/File;Lcom/runanywhere/sdk/foundation/SDKLogger;)V
       6: return

  static {};
    Code:
       0: getstatic     #843                // Field com/runanywhere/sdk/foundation/SDKLogger.Companion:Lcom/runanywhere/sdk/foundation/SDKLogger$Companion;
       3: invokevirtual #849                // Method com/runanywhere/sdk/foundation/SDKLogger$Companion.getModels:()Lcom/runanywhere/sdk/foundation/SDKLogger;
       6: putstatic     #114                // Field modelsLogger:Lcom/runanywhere/sdk/foundation/SDKLogger;
       9: new           #264                // class java/util/ArrayList
      12: dup
      13: invokespecial #326                // Method java/util/ArrayList."<init>":()V
      16: checkcast     #188                // class java/util/List
      19: putstatic     #160                // Field registeredModels:Ljava/util/List;
      22: new           #4                  // class java/lang/Object
      25: dup
      26: invokespecial #850                // Method java/lang/Object."<init>":()V
      29: putstatic     #156                // Field modelCacheLock:Ljava/lang/Object;
      32: new           #4                  // class java/lang/Object
      35: dup
      36: invokespecial #850                // Method java/lang/Object."<init>":()V
      39: putstatic     #243                // Field scanLock:Ljava/lang/Object;
      42: return
}
